Workbook

Sheet Start Here
A1: AI GTM OS — API acquisition plan
A2: Every third-party API the platform can connect to, in the order you should actually get them. Work top-down: finish the Prerequisites, then Phase P0 → P1 → P2 → P3. Track progress in the Status column of 'API Master List' — the Acquisition Plan sheet rolls it up automatically.
A5: THE ONE RULE | B5: Nothing here blocks you from using the product. Every provider left blank runs in SIMULATION mode, so the whole system is demoable today. You are buying REAL DATA and REAL EXECUTION, one channel at a time.
A7: START THESE ON DAY 1 (long lead times)
A8: 1. Email sending domains + warmup | B8: 2–3 WEEKS of warmup before you can send a single cold email. Longest pole in the project. Buy secondary domains today, create mailboxes, turn on warmup, then forget about it for 3 weeks.
A9: 2. Google Ads developer token | B9: Days to ~3 weeks of review. Apply the moment you have a Manager (MCC) account.
A10: 3. Meta Business Verification | B10: 1–4 weeks. Unlocks Meta Ads advanced access, the Ad Library AND WhatsApp in one go.
A11: 4. LinkedIn Marketing API | B11: 2–8 weeks and genuinely uncertain. Apply early; assume it may not land.
A13: PHASE LEGEND
A14: P0 — Day 1 | B14: Anthropic only. ~$50 of credits and every one of the 38 agents starts reasoning for real.
A15: P1 — Week 1 | B15: The wedge: Apollo + verifier + Instantly (outbound) · Google Ads (paid) · HubSpot (CRM) · Stripe + GA4 (revenue truth). This is a complete, working revenue loop.
A16: P2 — Week 2–4 | B16: Second channel + research: Meta Ads, Firecrawl, Tavily, SerpApi, Search Console, Resend, Gmail, Cal.com.
A17: P3 — Month 2–3 | B17: Scale: LinkedIn, creative/video generation, YouTube, TikTok, WhatsApp, PostHog.
A18: P4 — Later / optional | B18: Enterprise contracts (ZoomInfo, Semrush, Ahrefs) and alternatives you only need one of.
A20: 'ALTERNATIVE' MEANS PICK ONE | B20: Rows marked Alternative are pick-one-of-a-group: one CRM, one ESP, one sending platform, one email verifier, one SEO suite, one analytics tool. Do not buy the whole column.
A22: MINIMUM VIABLE SPEND | B22: ≈ $375/month of software gets the entire P0 + P1 loop running live on real data — Claude, Apollo, a verifier, Instantly, HubSpot, Stripe, GA4 and Google Ads. The ad budget itself is separate and will be the larger number. See the Cost Model sheet.
A24: WHERE THE KEYS GO | B24: Either paste them into the repo-root .env file (see '.env Key Map'), or enter them in the app at Integrations → click a provider → Save & test. Generate CREDENTIALS_ENCRYPTION_KEY first so UI-entered keys are encrypted at rest.
A26: SAFETY BEFORE YOU CONNECT ADS | B26: Settings → Control & guardrails: set the daily spend cap and leave 'AI can launch paid campaigns without approval' OFF until you trust the decision feed.

Sheet API Master List
A1: # | B1: Phase | C1: Category | D1: Provider | E1: What it powers | F1: Need | G1: Difficulty | H1: Lead time | I1: Prerequisite | J1: Cost model | K1: Est. $/mo | L1: Free tier | M1: Sign-up URL | N1: Docs URL | O1: How to acquire (steps) | P1: .env keys | Q1: Gotchas / watch-outs | R1: Status | S1: Owner | T1: Target date | U1: Notes
A2: 1 | B2: P0 | C2: AI Models | D2: Anthropic (Claude) | E2: Every agent's reasoning: AI CMO, ICP, copy, replies, decisions | F2: Required | G2: Instant | H2: 5 minutes | I2: Email + card | J2: Prepaid credits, per-token | K2: 150 | L2: $5 trial credit | M2: https://console.anthropic.com/settings/keys | N2: https://docs.anthropic.com | O2: 1) Sign up at console.anthropic.com. 2) Billing -> add payment method, buy credits ($50 is plenty to start). 3) API Keys -> Create Key -> copy once (shown only once). 4) Paste into ANTHROPIC_API_KEY in .env. 5) Restart Django; the sidebar badge flips from 'Simulation mode' to 'Claude live'. 6) Optional: set a monthly spend limit under Billing -> Limits. | P2: ANTHROPIC_API_KEY, ANTHROPIC_MODEL, ANTHROPIC_WORKER_MODEL | Q2: Set a spend limit before you let agents run on a schedule. Workspace-scoped keys let you separate dev/prod. | R2: Not started
A3: 2 | B3: P1 | C3: Prospecting | D3: Apollo.io | E3: Lead Discovery + Lead Enrichment: find and enrich ICP accounts/contacts | F3: Required | G3: Easy | H3: Same day | I3: Work email (blocks free domains) | J3: Seat subscription; API on paid plans | K3: 99 | L3: Free plan exists, API limited | M3: https://app.apollo.io/#/settings/integrations/api | N3: https://docs.apollo.io/reference | O3: 1) Sign up with a company email (Gmail/Outlook domains get rejected). 2) Upgrade to a plan with API access (Basic+ / Professional). 3) Settings -> Integrations -> API -> Create new key. 4) Note your monthly credit allowance and per-endpoint rate limits. 5) Paste into APOLLO_API_KEY. 6) Confirm on /integrations -> Apollo -> Test connection. | P3: APOLLO_API_KEY | Q3: Export/enrichment credits are the real constraint, not rate limits. API access is gated behind paid tiers — check the current tier before buying. | R3: Not started
A4: 3 | B4: P1 | C4: Email Verification | D4: MillionVerifier | E4: Lead Verification Agent: deliverability gate before any send | F4: Required | G4: Instant | H4: 5 minutes | I4: None | J4: Pay-as-you-go credits (no expiry) | K4: 30 | L4: 100 free credits | M4: https://www.millionverifier.com | N4: https://developer.millionverifier.com | O4: 1) Sign up. 2) Buy a credit pack (10k credits is a cheap start — credits don't expire). 3) Dashboard -> API -> copy key. 4) Paste into MILLIONVERIFIER_API_KEY. 5) Keep EMAIL_VERIFICATION_WATERFALL ordered cheapest-first. | P4: MILLIONVERIFIER_API_KEY, EMAIL_VERIFICATION_WATERFALL | Q4: Cheapest of the three verifiers — good default. Pick ONE to start; the waterfall only needs a second provider once volume justifies it. | R4: Not started
A5: 4 | B5: P1 | C5: Email Verification | D5: ZeroBounce | E5: Lead Verification Agent (waterfall step 1) | F5: Alternative | G5: Instant | H5: 5 minutes | I5: None | J5: Credit packs or monthly | K5: 40 | L5: 100 free/month | M5: https://www.zerobounce.net | N5: https://www.zerobounce.net/docs/ | O5: 1) Sign up. 2) Buy credits. 3) API -> copy key. 4) Paste into ZEROBOUNCE_API_KEY. | P5: ZEROBOUNCE_API_KEY | Q5: Pick ONE verifier to start (ZeroBounce / NeverBounce / MillionVerifier). Adding all three only helps at scale. | R5: Not started
A6: 5 | B6: P1 | C6: Email Verification | D6: NeverBounce | E6: Lead Verification Agent (waterfall step 2) | F6: Alternative | G6: Instant | H6: 5 minutes | I6: None | J6: Pay-as-you-go | K6: 40 | L6: 1,000 free on signup | M6: https://app.neverbounce.com | N6: https://developers.neverbounce.com | O6: 1) Sign up. 2) Add credits. 3) Account -> API -> generate key. 4) Paste into NEVERBOUNCE_API_KEY. | P6: NEVERBOUNCE_API_KEY | Q6: Alternative to MillionVerifier/ZeroBounce — do not buy all three on day one. | R6: Not started
A7: 6 | B7: P1 | C7: Outbound Sending | D7: Instantly | E7: AI Sequence Agent: mailbox rotation, warmup, throttled sends, reply capture | F7: Required | G7: Medium | H7: 1-2 days setup, 2-3 weeks warmup | I7: Sending domains + mailboxes | J7: Per-seat + per-mailbox | K7: 97 | L7: 14-day trial | M7: https://app.instantly.ai | N7: https://developer.instantly.ai | O7: 1) Buy 2-3 lookalike sending domains (NOT your primary domain) e.g. get-acme.com, tryacme.com. 2) Create 2-3 mailboxes per domain in Google Workspace or Microsoft 365. 3) Set SPF, DKIM and DMARC on every domain. 4) Sign up for Instantly, connect all mailboxes, switch warmup ON and leave it for 2-3 weeks before real sends. 5) Settings -> Integrations -> API -> copy key -> INSTANTLY_API_KEY. 6) Keep OUTBOUND_DAILY_LIMIT_PER_MAILBOX at 30-40. | P7: INSTANTLY_API_KEY, OUTBOUND_PROVIDER, OUTBOUND_DAILY_LIMIT_PER_MAILBOX | Q7: WARMUP IS THE LONG POLE — start domains + warmup on day 1 even if everything else waits. Never send cold outbound from your primary domain. Check local law (GDPR/CAN-SPAM/CASL) for your target geos. | R7: Not started
A8: 7 | B8: P1 | C8: CRM | D8: HubSpot | E8: CRM Agent + Attribution: contacts, companies, deals, notes, tasks | F8: Required | G8: Easy | H8: 30 minutes | I8: HubSpot account (free tier works) | J8: Free CRM; paid for automation | K8: 0 | L8: Free CRM tier is enough | M8: https://app.hubspot.com | N8: https://developers.hubspot.com/docs/api/overview | O8: 1) Create a free HubSpot account. 2) Settings -> Integrations -> Private Apps -> Create private app. 3) Scopes: crm.objects.contacts/companies/deals read+write, crm.schemas read, plus tasks/notes (engagements). 4) Create app -> copy the access token (shown once). 5) Paste into HUBSPOT_ACCESS_TOKEN and set CRM_PROVIDER=hubspot. 6) Test on /integrations -> HubSpot. | P8: HUBSPOT_ACCESS_TOKEN, HUBSPOT_PORTAL_ID, CRM_PROVIDER | Q8: Private-app tokens are simpler than OAuth for a single workspace. If you add scopes later you must re-copy the token. | R8: Not started
A9: 8 | B9: P1 | C9: Analytics & Revenue | D9: Stripe | E9: Attribution + Revenue Intelligence: the closed-revenue source of truth | F9: Required | G9: Instant | H9: Same day (live keys need KYC) | I9: Registered business for live mode | J9: % of transactions (no API fee) | K9: 0 | L9: Test mode free forever | M9: https://dashboard.stripe.com/apikeys | N9: https://stripe.com/docs/api | O9: 1) Create a Stripe account. 2) Developers -> API keys -> copy the SECRET key (sk_test_ for testing, sk_live_ after business verification). 3) Developers -> Webhooks -> add endpoint <PUBLIC_API_URL>/api/webhooks/stripe/ -> copy the signing secret. 4) Paste STRIPE_SECRET_KEY + STRIPE_WEBHOOK_SECRET. 5) Start in test mode with seeded data. | P9: STRIPE_SECRET_KEY, STRIPE_WEBHOOK_SECRET | Q9: Use restricted keys (read-only on charges/subscriptions) rather than the full secret key. Skip if you don't bill through Stripe — use Shopify or CRM closed-won instead. | R9: Not started
A10: 9 | B10: P1 | C10: Paid Media | D10: Google Ads | E10: Paid Media Agent + Autonomous Media Buyer: Search, Display, YouTube | F10: Required | G10: Hard | H10: 1-3 weeks (token review) | I10: Google Ads account + Manager (MCC) + billing | J10: Ad spend only; API free | K10: 0 | L10: API is free; you pay media | M10: https://ads.google.com | N10: https://developers.google.com/google-ads/api/docs/start | O10: 1) Create a Google Ads account AND a Manager (MCC) account; link the ad account to the MCC. Add billing. 2) In the MCC: Tools -> Setup -> API Center -> apply for a developer token. You start with Test access. 3) Apply for Basic access: describe the tool, your company site, and how you comply with the Required Minimum Functionality policy. Review typically takes a few business days to ~3 weeks. 4) In Google Cloud Console: create a project, enable the Google Ads API, configure the OAuth consent screen, create an OAuth client ID (Desktop or Web). 5) Generate a refresh token (OAuth Playground with your own client ID, or the SDK's auth script). 6) Fill GOOGLE_ADS_DEVELOPER_TOKEN, CLIENT_ID, CLIENT_SECRET, REFRESH_TOKEN, LOGIN_CUSTOMER_ID (MCC, digits only), CUSTOMER_ID (target account, digits only). | P10: GOOGLE_ADS_DEVELOPER_TOKEN, GOOGLE_ADS_CLIENT_ID, GOOGLE_ADS_CLIENT_SECRET, GOOGLE_ADS_REFRESH_TOKEN, GOOGLE_ADS_LOGIN_CUSTOMER_ID, GOOGLE_ADS_CUSTOMER_ID | Q10: APPLY FOR THE DEVELOPER TOKEN ON DAY 1 — it is the slowest item in Week 1. Test access only works against test accounts, so you cannot touch real campaigns until Basic access lands. Customer IDs must have dashes stripped. | R10: Not started
A11: 10 | B11: P1 | C11: Analytics & Revenue | D11: Google Analytics 4 | E11: Analytics Agent + CRO: traffic, conversions, journey stitching | F11: Recommended | G11: Easy | H11: 1 hour | I11: GA4 property + Google Cloud project | J11: Free (GA4 standard) | K11: 0 | L11: Free | M11: https://console.cloud.google.com | N11: https://developers.google.com/analytics/devguides/reporting/data/v1 | O11: 1) Google Cloud Console -> create/select a project -> enable 'Google Analytics Data API'. 2) IAM -> Service Accounts -> create one -> Keys -> Add key -> JSON -> download. 3) In GA4 Admin -> Property Access Management -> add the service-account email as Viewer. 4) Copy the GA4 property ID (Admin -> Property Settings, numeric). 5) Set GA4_PROPERTY_ID and GOOGLE_SERVICE_ACCOUNT_JSON_PATH (keep the JSON outside git). | P11: GA4_PROPERTY_ID, GOOGLE_SERVICE_ACCOUNT_JSON_PATH, GOOGLE_SERVICE_ACCOUNT_JSON | Q11: The same service account can also serve Search Console — reuse it. Never commit the JSON file. | R11: Not started
A12: 11 | B12: P1 | C12: Alerts & Ops | D12: Slack | E12: Compliance + AI CMO: approval requests and 'needs human sign-off' alerts | F12: Recommended | G12: Easy | H12: 20 minutes | I12: Slack workspace admin | J12: Free | K12: 0 | L12: Free | M12: https://api.slack.com/apps | N12: https://api.slack.com/quickstart | O12: 1) api.slack.com/apps -> Create New App -> From scratch. 2) OAuth & Permissions -> Bot Token Scopes: chat:write, chat:write.public, channels:read. 3) Install to Workspace -> copy the Bot User OAuth Token (xoxb-...). 4) Invite the bot to your alerts channel. 5) Set SLACK_BOT_TOKEN and SLACK_ALERTS_CHANNEL. | P12: SLACK_BOT_TOKEN, SLACK_ALERTS_CHANNEL, SLACK_SIGNING_SECRET | Q12: Without this, approvals live only in the Command Centre — fine for one operator, painful for a team. | R12: Not started
A13: 12 | B13: P2 | C13: Paid Media | D13: Meta Ads (Facebook + Instagram) | E13: Paid Media Agent, Creative Testing, Competitor ad monitoring (Ad Library) | F13: Required | G13: Hard | H13: 1-4 weeks (verification) | I13: Meta Business Account + Page + verified business | J13: Ad spend only; API free | K13: 0 | L13: API free; you pay media | M13: https://developers.facebook.com/apps | N13: https://developers.facebook.com/docs/marketing-apis | O13: 1) Create a Meta Business Account at business.facebook.com; add your Facebook Page, Instagram account and Ad Account. 2) START BUSINESS VERIFICATION IMMEDIATELY (Business Settings -> Security Centre): you need your legal business name, registration/incorporation document and a document showing the business address or phone. This is the slow part. 3) developers.facebook.com -> Create App -> type 'Business' -> link it to the Business Account. 4) Add the 'Marketing API' product. Development access works instantly on ad accounts you own. 5) Business Settings -> Users -> System Users -> Add -> Admin -> Generate New Token. Scopes: ads_management, ads_read, business_management, pages_show_list, pages_manage_posts, instagram_basic, instagram_content_publish. 6) Assign the System User to the Ad Account, Page and Instagram account. 7) For live traffic at scale, submit App Review for Advanced Access on ads_management. 8) Fill META_APP_ID, META_APP_SECRET, META_ACCESS_TOKEN, META_AD_ACCOUNT_ID (act_ prefix), META_PAGE_ID, META_INSTAGRAM_ACCOUNT_ID, META_PIXEL_ID. | P13: META_APP_ID, META_APP_SECRET, META_ACCESS_TOKEN, META_AD_ACCOUNT_ID, META_PIXEL_ID, META_PAGE_ID, META_INSTAGRAM_ACCOUNT_ID, META_API_VERSION | Q13: Business Verification gates Advanced Access, WhatsApp Cloud API and the Ad Library — start it the same day you start Google Ads. Use a System User token (long-lived), never a personal user token. Ad account ID must keep the 'act_' prefix. | R13: Not started
... A68: 67 | B68: P4 | C68: Storage | D68: AWS S3 / Cloudflare R2 | E68: Storage for generated creatives, videos and exports | F68: Optional | G68: Easy | H68: 30 minutes | I68: AWS or Cloudflare account | J68: Per GB stored + egress | K68: 5 | L68: R2 has free egress | M68: https://aws.amazon.com/s3/ | N68: https://docs.aws.amazon.com/s3/ | O68: 1) Create a bucket (private). 2) Create an IAM user with least-privilege access to that bucket only. 3) Generate an access key pair. 4) Fill AWS_ACCESS_KEY_ID, AWS_SECRET_ACCESS_KEY, AWS_STORAGE_BUCKET_NAME, AWS_S3_REGION_NAME and set STORAGE_BACKEND=s3. | P68: AWS_ACCESS_KEY_ID, AWS_SECRET_ACCESS_KEY, AWS_STORAGE_BUCKET_NAME, AWS_S3_REGION_NAME, STORAGE_BACKEND | Q68: Local storage is the default and fine until you generate video at volume. R2 avoids egress fees. | R68: Not started

Sheet Acquisition Plan
A1: 30-day acquisition plan
A2: Roll-up counts are live formulas over the Status column of 'API Master List' — update status there, these numbers follow.
A4: Phase | B4: What it unlocks | C4: Items | D4: Live | E4: In flight | F4: Not started | G4: % complete | H4: Est. $/mo
A5: P0 | B5: Agents reason for real instead of simulating | C5: =COUNTIF('API Master List'!$B$2:$B$68,"P0") | D5: =COUNTIFS('API Master List'!$B$2:$B$68,"P0",'API Master List'!$R$2:$R$68,"Live") | E5: =COUNTIFS('API Master List'!$B$2:$B$68,"P0",'API Master List'!$R$2:$R$68,"Applied")+COUNTIFS('API Master List'!$B$2:$B$68,"P0",'API Master List'!$R$2:$R$68,"In review")+COUNTIFS('API Master List'!$B$2:$B$68,"P0",'API Master List'!$R$2:$R$68,"Approved") | F5: =COUNTIFS('API Master List'!$B$2:$B$68,"P0",'API Master List'!$R$2:$R$68,"Not started") | G5: =IF(C5=0,0,D5/C5) | H5: =SUMIFS('API Master List'!$K$2:$K$68,'API Master List'!$B$2:$B$68,"P0",'API Master List'!$F$2:$F$68,"Required")+SUMIFS('API Master List'!$K$2:$K$68,'API Master List'!$B$2:$B$68,"P0",'API Master List'!$F$2:$F$68,"Recommended")
A6: P1 | B6: Complete revenue loop: outbound + Google Ads + CRM + revenue truth | C6: =COUNTIF('API Master List'!$B$2:$B$68,"P1") | D6: =COUNTIFS('API Master List'!$B$2:$B$68,"P1",'API Master List'!$R$2:$R$68,"Live") | E6: =COUNTIFS('API Master List'!$B$2:$B$68,"P1",'API Master List'!$R$2:$R$68,"Applied")+COUNTIFS('API Master List'!$B$2:$B$68,"P1",'API Master List'!$R$2:$R$68,"In review")+COUNTIFS('API Master List'!$B$2:$B$68,"P1",'API Master List'!$R$2:$R$68,"Approved") | F6: =COUNTIFS('API Master List'!$B$2:$B$68,"P1",'API Master List'!$R$2:$R$68,"Not started") | G6: =IF(C6=0,0,D6/C6) | H6: =SUMIFS('API Master List'!$K$2:$K$68,'API Master List'!$B$2:$B$68,"P1",'API Master List'!$F$2:$F$68,"Required")+SUMIFS('API Master List'!$K$2:$K$68,'API Master List'!$B$2:$B$68,"P1",'API Master List'!$F$2:$F$68,"Recommended")
A7: P2 | B7: Second paid channel, real research data, lifecycle email | C7: =COUNTIF('API Master List'!$B$2:$B$68,"P2") | D7: =COUNTIFS('API Master List'!$B$2:$B$68,"P2",'API Master List'!$R$2:$R$68,"Live") | E7: =COUNTIFS('API Master List'!$B$2:$B$68,"P2",'API Master List'!$R$2:$R$68,"Applied")+COUNTIFS('API Master List'!$B$2:$B$68,"P2",'API Master List'!$R$2:$R$68,"In review")+COUNTIFS('API Master List'!$B$2:$B$68,"P2",'API Master List'!$R$2:$R$68,"Approved") | F7: =COUNTIFS('API Master List'!$B$2:$B$68,"P2",'API Master List'!$R$2:$R$68,"Not started") | G7: =IF(C7=0,0,D7/C7) | H7: =SUMIFS('API Master List'!$K$2:$K$68,'API Master List'!$B$2:$B$68,"P2",'API Master List'!$F$2:$F$68,"Required")+SUMIFS('API Master List'!$K$2:$K$68,'API Master List'!$B$2:$B$68,"P2",'API Master List'!$F$2:$F$68,"Recommended")
A8: P3 | B8: Scale: LinkedIn, video creative, more social, WhatsApp | C8: =COUNTIF('API Master List'!$B$2:$B$68,"P3") | D8: =COUNTIFS('API Master List'!$B$2:$B$68,"P3",'API Master List'!$R$2:$R$68,"Live") | E8: =COUNTIFS('API Master List'!$B$2:$B$68,"P3",'API Master List'!$R$2:$R$68,"Applied")+COUNTIFS('API Master List'!$B$2:$B$68,"P3",'API Master List'!$R$2:$R$68,"In review")+COUNTIFS('API Master List'!$B$2:$B$68,"P3",'API Master List'!$R$2:$R$68,"Approved") | F8: =COUNTIFS('API Master List'!$B$2:$B$68,"P3",'API Master List'!$R$2:$R$68,"Not started") | G8: =IF(C8=0,0,D8/C8) | H8: =SUMIFS('API Master List'!$K$2:$K$68,'API Master List'!$B$2:$B$68,"P3",'API Master List'!$F$2:$F$68,"Required")+SUMIFS('API Master List'!$K$2:$K$68,'API Master List'!$B$2:$B$68,"P3",'API Master List'!$F$2:$F$68,"Recommended")
A9: P4 | B9: Enterprise contracts and pick-one alternatives | C9: =COUNTIF('API Master List'!$B$2:$B$68,"P4") | D9: =COUNTIFS('API Master List'!$B$2:$B$68,"P4",'API Master List'!$R$2:$R$68,"Live") | E9: =COUNTIFS('API Master List'!$B$2:$B$68,"P4",'API Master List'!$R$2:$R$68,"Applied")+COUNTIFS('API Master List'!$B$2:$B$68,"P4",'API Master List'!$R$2:$R$68,"In review")+COUNTIFS('API Master List'!$B$2:$B$68,"P4",'API Master List'!$R$2:$R$68,"Approved") | F9: =COUNTIFS('API Master List'!$B$2:$B$68,"P4",'API Master List'!$R$2:$R$68,"Not started") | G9: =IF(C9=0,0,D9/C9) | H9: =SUMIFS('API Master List'!$K$2:$K$68,'API Master List'!$B$2:$B$68,"P4",'API Master List'!$F$2:$F$68,"Required")+SUMIFS('API Master List'!$K$2:$K$68,'API Master List'!$B$2:$B$68,"P4",'API Master List'!$F$2:$F$68,"Recommended")
B10: TOTAL (Required + Recommended only) | C10: =SUM(C5:C9) | D10: =SUM(D5:D9) | E10: =SUM(E5:E9) | F10: =SUM(F5:F9) | G10: =IF(C10=0,0,D10/C10) | H10: =SUM(H5:H9)
A13: WEEK BY WEEK
A14: When | B14: Do this | C14: Why now
A15: Day 1 (morning) | B15: Buy 2–3 secondary sending domains, create 2–3 mailboxes each, set SPF/DKIM/DMARC, sign up for Instantly, connect all mailboxes, switch warmup ON. | C15: Warmup takes 2–3 weeks of calendar time. Everything else can be done while it runs; this cannot be rushed.
A16: Day 1 (afternoon) | B16: Create the Google Ads Manager (MCC) account and apply for the developer token. Create the Meta Business Account and start Business Verification. | C16: Both are review queues measured in days-to-weeks. Get in the queue before you need them.
A17: Day 1 (evening) | B17: Anthropic key + $50 of credits. Generate CREDENTIALS_ENCRYPTION_KEY. Set spend caps in Settings → Control & guardrails. | C17: Five minutes and all 38 agents stop simulating and start reasoning on your real business.
A18: Day 2–3 | B18: Apollo (paid tier for API) + one email verifier + HubSpot private app + Stripe test keys. | C18: This is the data spine: find → enrich → verify → CRM → revenue. Cheap and instant.
A19: Day 3–5 | B19: Firecrawl + Tavily. Run the Business Intelligence and Competitor Intelligence agents. | C19: ≈$50 turns the knowledge graph from demo data into YOUR business, product, pricing and competitors. Highest leverage purchase in the list.
A20: Week 1 end | B20: GA4 + Search Console service account. Slack bot for approvals. | C20: Closes the measurement loop and gets approval requests out of the dashboard and into your day.
A21: Week 2 | B21: Google Ads token should land → wire it up and launch one high-intent Search campaign. Add Resend for lifecycle email. Add Cal.com for meeting booking. | C21: First real paid channel plus a booking path for the AI SDR.
A22: Week 3 | B22: Warmup finishes → launch the first real outbound sequence, throttled to 30–40/mailbox/day. Meta verification should land → connect Meta Ads. | C22: Now both halves of the wedge (outbound + paid) are live and attributable.
A23: Week 4 | B23: Review the decision feed and attribution. Cut whatever is not working. Apply for LinkedIn Marketing API if B2B enterprise is your motion. | C23: First real reallocation decision from the Autonomous Media Buyer, made on your own data.
A24: Month 2–3 | B24: Add creative generation (fal.ai / ElevenLabs), YouTube or TikTok if relevant, PostHog for CRO, WhatsApp if your geo uses it. | C24: Only scale channels once the wedge has a proven CAC you are happy to spend more against.

Sheet Prerequisites
A1: Prerequisites — do these before the APIs
A2: These are not APIs. They are the accounts, documents and decisions that gate the API applications. Skipping them is the single most common reason an acquisition plan stalls in week 2.
A4: # | B4: Prerequisite | C4: Why it blocks you | D4: Owner | E4: Lead time | F4: How to do it | G4: Status
A5: 1 | B5: Legal business entity + registration document | C5: Meta Business Verification, Google Ads billing, ZoomInfo/Semrush contracts, Stripe live mode all require it | D5: Founder / Finance | E5: Already done, or weeks | F5: Have the incorporation certificate, tax ID and a document showing the business address ready as PDFs before you start any verification. | G5: Not started
A6: 2 | B6: Company domain with DNS access | C6: Domain authentication for every email provider, GSC verification, landing-page subdomains | D6: Founder / IT | E6: Same day | F6: Make sure you (not an agency) can add TXT/CNAME records. Check now, not on the day you need it. | G6: Not started
A7: 3 | B7: 2-3 SECONDARY sending domains + mailboxes | C7: Cold outbound must never run on your primary domain — a spam trap can kill your real email | D7: Growth | E7: 1 day to buy, 2-3 WEEKS to warm | F7: Buy lookalike domains (get-acme.com, tryacme.com, acme-hq.com). Create 2-3 mailboxes each in Google Workspace or M365. Set SPF, DKIM and DMARC on all of them. Connect to Instantly and turn warmup on. START THIS FIRST — it is the longest-lead item in the whole project. | G7: Not started
A8: 4 | B8: Google Ads Manager (MCC) account | C8: Required before you can even apply for a developer token | D8: Growth | E8: 1 hour | F8: Create at ads.google.com/home/tools/manager-accounts, then link your ad account to it. | G8: Not started
A9: 5 | B9: Meta Business Account + Page + Ad Account + Instagram | C9: Everything Meta (Ads, Ad Library, WhatsApp) hangs off this | D9: Growth | E9: 1 day + verification wait | F9: Set up at business.facebook.com, then immediately start Business Verification in Security Centre. | G9: Not started
A10: 6 | B10: LinkedIn Company Page with admin rights | C10: Required to create and verify a LinkedIn developer app | D10: Founder | E10: 1 day | F10: You must be a Page admin. Page verification inside the developer app needs an admin to click a link. | G10: Not started
A11: 7 | B11: Google Cloud project + service account | C11: Shared by GA4, Search Console, Gmail, YouTube and Google Ads OAuth | D11: Engineering | E11: 1 hour | F11: Create ONE project and reuse it. Download the service-account JSON, store it outside git, reference it via GOOGLE_SERVICE_ACCOUNT_JSON_PATH. | G11: Not started
A12: 8 | B12: Privacy policy + terms + cookie consent on your site | C12: App reviews (Meta, Google, LinkedIn, TikTok) check for these; GDPR requires them | D12: Founder / Legal | E12: 2-3 days | F12: Publish them at stable URLs before you submit any app review — reviewers do check. | G12: Not started
A13: 9 | B13: Outbound compliance position for your target geos | C13: GDPR (EU), CAN-SPAM (US), CASL (Canada), PECR (UK) all constrain cold outbound differently | D13: Founder / Legal | E13: 1 week | F13: Decide your legal basis per geography, add a working unsubscribe to every sequence, keep a suppression list, and honour opt-outs immediately. The Lead Verification + Compliance agents enforce this only if you configure it. | G13: Not started
A14: 10 | B14: CREDENTIALS_ENCRYPTION_KEY generated | C14: Connector credentials saved in the UI are stored in plaintext without it | D14: Engineering | E14: 1 minute | F14: Run: python -c "from cryptography.fernet import Fernet; print(Fernet.generate_key().decode())" and put the result in CREDENTIALS_ENCRYPTION_KEY. Do this BEFORE saving any key in the Integrations screen. | G14: Not started
A15: 11 | B15: Spend guardrails agreed | C15: Full-autonomy mode can spend real money on real ad platforms | D15: Founder | E15: 30 minutes | F15: Set DEFAULT_DAILY_SPEND_CAP and the per-agent modes in Settings -> Control & guardrails BEFORE connecting any ad platform. Keep AI_CAN_LAUNCH_PAID_WITHOUT_APPROVAL off until you trust the output. | G15: Not started

Sheet Cost Model
A1: Indicative monthly cost
A2: List prices for small-team tiers, USD, early 2026 — ALWAYS verify on the vendor's pricing page before budgeting. Excludes the advertising budget itself, which is the biggest line item once you go live.
A4: Scenario | B4: What's included | C4: Software $/mo | D4: Notes
A5: Demo / simulation | B5: Nothing. Every provider blank. | C5: 0 | D5: The full product is usable and demoable — agents produce deterministic simulated output.
A6: P0 — agents thinking | B6: Anthropic only | C6: =SUMIFS('API Master List'!$K$2:$K$68,'API Master List'!$B$2:$B$68,"P0") | D6: ≈$50 of credits goes a long way at this volume. Set a spend limit in the Anthropic console.
A7: P0+P1 — the wedge live | B7: Anthropic, Apollo, verifier, Instantly, HubSpot, Stripe, GA4, Google Ads, Slack | C7: =SUMIFS('API Master List'!$K$2:$K$68,'API Master List'!$B$2:$B$68,"P0")+SUMIFS('API Master List'!$K$2:$K$68,'API Master List'!$B$2:$B$68,"P1",'API Master List'!$F$2:$F$68,"Required")+SUMIFS('API Master List'!$K$2:$K$68,'API Master List'!$B$2:$B$68,"P1",'API Master List'!$F$2:$F$68,"Recommended") | D7: MINIMUM VIABLE REAL SYSTEM. Complete revenue loop on real data. Add your ad budget on top.
A8: + P2 — second channel | B8: Meta Ads, Firecrawl, Tavily, SerpApi, GSC, Resend, Gmail, Cal.com | C8: =C7+SUMIFS('API Master List'!$K$2:$K$68,'API Master List'!$B$2:$B$68,"P2",'API Master List'!$F$2:$F$68,"Required")+SUMIFS('API Master List'!$K$2:$K$68,'API Master List'!$B$2:$B$68,"P2",'API Master List'!$F$2:$F$68,"Recommended") | D8: Two paid channels, real research, lifecycle email.
A9: + P3 — scaling | B9: LinkedIn, creative generation, YouTube, TikTok, WhatsApp, PostHog | C9: =C8+SUMIFS('API Master List'!$K$2:$K$68,'API Master List'!$B$2:$B$68,"P3",'API Master List'!$F$2:$F$68,"Required")+SUMIFS('API Master List'!$K$2:$K$68,'API Master List'!$B$2:$B$68,"P3",'API Master List'!$F$2:$F$68,"Recommended")+SUMIFS('API Master List'!$K$2:$K$68,'API Master List'!$B$2:$B$68,"P3",'API Master List'!$F$2:$F$68,"Optional") | D9: LinkedIn/YouTube/TikTok/PostHog APIs are free — the increase here is creative generation (usage-based, so treat it as a floor). Only scale once the wedge shows a CAC you want to spend more against.
A10: Everything incl. optional | B10: All Required + Recommended + Optional rows | C10: =SUMIFS('API Master List'!$K$2:$K$68,'API Master List'!$F$2:$F$68,"Required")+SUMIFS('API Master List'!$K$2:$K$68,'API Master List'!$F$2:$F$68,"Recommended")+SUMIFS('API Master List'!$K$2:$K$68,'API Master List'!$F$2:$F$68,"Optional") | D10: You will almost certainly never need this — 'Alternative' rows are pick-one.
A13: COST NOTES
A14: • Ad spend is NOT in these numbers. Budget it separately — it will dwarf the software cost.
A15: • Claude usage scales with how often agents run. Start agents manually or daily, not hourly. Use the worker model (claude-sonnet-5) for bulk personalisation — it's already wired in ANTHROPIC_WORKER_MODEL.
A16: • Apollo/ZoomInfo cost is driven by enrichment CREDITS, not seats. Verify before sending to avoid burning credits on bad data.
A17: • Semrush and Ahrefs gate their APIs behind top-tier plans (~$500/mo each). SerpApi + Search Console cover most of the same ground for under $100.
A18: • Video generation is the most volatile line item. Gate renders behind the Creative Testing Agent so you only render variants of proven winners.
A19: • Set a hard daily spend cap in Settings → Control & guardrails BEFORE connecting any ad platform.

Sheet .env Key Map
A1: .env key map
A2: Every variable in .env.example, the section it lives in, and which provider fills it. Keys with no provider are platform settings you set yourself — no signup needed.
A4: Section | B4: .env variable | C4: Filled by | D4: Type | E4: Required to run?
A5: 1. CORE PLATFORM | B5: DJANGO_SECRET_KEY | C5: — | D5: Platform setting | E5: Yes
A6: 1. CORE PLATFORM | B6: DJANGO_DEBUG | C6: — | D6: Platform setting | E6: Has a default
A7: 1. CORE PLATFORM | B7: DJANGO_ALLOWED_HOSTS | C7: — | D7: Platform setting | E7: Has a default
A8: 1. CORE PLATFORM | B8: CORS_ALLOWED_ORIGINS | C8: — | D8: Platform setting | E8: Has a default
A9: 1. CORE PLATFORM | B9: DATABASE_URL | C9: — | D9: Platform setting | E9: Has a default
A10: 1. CORE PLATFORM | B10: REDIS_URL | C10: — | D10: Platform setting | E10: Has a default
A11: 1. CORE PLATFORM | B11: PUBLIC_APP_URL | C11: — | D11: Platform setting | E11: Has a default
A12: 1. CORE PLATFORM | B12: PUBLIC_API_URL | C12: — | D12: Platform setting | E12: Has a default
A13: 1. CORE PLATFORM | B13: JWT_ACCESS_MINUTES | C13: — | D13: Platform setting | E13: Has a default
A14: 1. CORE PLATFORM | B14: JWT_REFRESH_DAYS | C14: — | D14: Platform setting | E14: Has a default
A15: 1. CORE PLATFORM | B15: CREDENTIALS_ENCRYPTION_KEY | C15: — | D15: Platform setting | E15: Yes
... A197: 14. FRONTEND (Vite reads only VITE_* vars - these live in frontend/.env) | B197: VITE_DEMO_PASSWORD | C197: — | D197: Frontend setting | E197: Has a default
